waylay/services/storage/models/__init__.py
waylay/services/storage/models/auth.py
waylay/services/storage/models/authentication_config.py
waylay/services/storage/models/bucket.py
waylay/services/storage/models/bucket_configuration.py
waylay/services/storage/models/bucket_listing.py
waylay/services/storage/models/bucket_object.py
waylay/services/storage/models/bucket_object_listing.py
waylay/services/storage/models/bucketcreationstatus.py
waylay/services/storage/models/bucketpolicystatus.py
waylay/services/storage/models/channel.py
waylay/services/storage/models/channeltype.py
waylay/services/storage/models/event_filter.py
waylay/services/storage/models/expiry.py
waylay/services/storage/models/hal_entity.py
waylay/services/storage/models/hal_link.py
waylay/services/storage/models/http_validation_error.py
waylay/services/storage/models/httpmethod.py
waylay/services/storage/models/links_value.py
waylay/services/storage/models/location_inner.py
waylay/services/storage/models/notification_queue_status.py
waylay/services/storage/models/notification_queue_status_report.py
waylay/services/storage/models/object.py
waylay/services/storage/models/payload_config.py
waylay/services/storage/models/py.typed
waylay/services/storage/models/queuesetupstatus.py
waylay/services/storage/models/response_list.py
waylay/services/storage/models/sign.py
waylay/services/storage/models/store.py
waylay/services/storage/models/storetype.py
waylay/services/storage/models/subscription_config.py
waylay/services/storage/models/subscriptions.py
waylay/services/storage/models/subscriptions_listing.py
waylay/services/storage/models/system_channel_config.py
waylay/services/storage/models/system_channel_config_type.py
waylay/services/storage/models/tenant_status_report.py
waylay/services/storage/models/validation_error.py
waylay/services/storage/models/venttype.py
waylay/services/storage/models/web_script_channel_config.py
waylay/services/storage/models/web_script_channel_config_type.py
waylay_sdk_storage_types-0.5.2.20241025.dist-info/LICENSE.txt
waylay_sdk_storage_types-0.5.2.20241025.dist-info/METADATA
waylay_sdk_storage_types-0.5.2.20241025.dist-info/WHEEL
waylay_sdk_storage_types-0.5.2.20241025.dist-info/top_level.txt
waylay_sdk_storage_types-0.5.2.20241025.dist-info/RECORD
