Metadata-Version: 2.1
Name: waylay-sdk-storage-types
Version: 0.5.2.20241025
Summary: Waylay Storage Types 
Author-email: Waylay <info@waylay.io>
License: ISC License (ISC)
Project-URL: Homepage, https://www.waylay.io/
Project-URL: Documentation, https://docs.waylay.io/#/api/?id=software-development-kits
Project-URL: Repository, https://github.com/waylayio/waylay-sdk-storage-py.git
Project-URL: Openapi Specification, https://docs.waylay.io/openapi/public/redocly/storage.html
Keywords: Waylay Storage,Types
Requires-Python: >=3.9
License-File: LICENSE.txt
Requires-Dist: waylay-sdk-core~=0.3.2
Requires-Dist: waylay-sdk-storage==0.5.2.20241025
Requires-Dist: pydantic~=2.6
Requires-Dist: typing-extensions~=4.10
Requires-Dist: eval-type-backport~=0.1.3; python_version < "3.10"
Provides-Extra: dev
Requires-Dist: mypy; extra == "dev"
Requires-Dist: ruff; extra == "dev"
Requires-Dist: types-python-jose; extra == "dev"
Requires-Dist: types-appdirs; extra == "dev"
Requires-Dist: types-python-dateutil; extra == "dev"
Requires-Dist: pytest; extra == "dev"
Requires-Dist: pytest-mock; extra == "dev"
Requires-Dist: pytest-httpx; extra == "dev"
Requires-Dist: pytest-asyncio; extra == "dev"
Requires-Dist: starlette; extra == "dev"
Requires-Dist: python-multipart; extra == "dev"
Requires-Dist: typeguard; extra == "dev"
Requires-Dist: pyyaml; extra == "dev"
Requires-Dist: jsf>=0.11.1; extra == "dev"
